<busstate version="1.00" timestamp="2025-04-04 17:31:27">
<bus time="250404173121" lat="64.0972495833333" lon="-21.9207365" head="207.49" fix="2" route="1" stop="13001201" next="13001523" code="6" />
<bus time="250404173125" lat="64.1465058833333" lon="-21.9555401666667" head="137.93" fix="2" route="13" stop="90000281" next="90000179" code="6" />
<bus time="250404173126" lat="64.1358105166667" lon="-21.7608976666667" head="201.53" fix="2" route="15" stop="90000772" next="90000645" code="6" />
<bus time="250404173123" lat="64.12395275" lon="-21.8186603333333" head="87.98" fix="2" route="5" stop="90000018" next="90000398" code="6" />
<bus time="250404173124" lat="64.1017003833333" lon="-21.823496" head="234.29" fix="1" route="12" stop="90000526" next="90000383" code="7" />
<bus time="250404173126" lat="64.1325700666667" lon="-21.8734795" head="198.80" fix="2" route="14" stop="90000224" next="90000225" code="6" />
<bus time="250404173126" lat="64.0996053333333" lon="-21.8280256666667" head="299.84" fix="2" route="12" stop="90000343" next="90000344" code="6" />
<bus time="250404173123" lat="64.1128969166667" lon="-21.8427863333333" head="203.69" fix="2" route="4" stop="10000818" next="90000860" code="6" />
<bus time="250404173126" lat="64.1206796" lon="-21.8467695" head="348.14" fix="2" route="12" stop="90000151" next="90000155" code="6" />
<bus time="250404173123" lat="64.12407735" lon="-21.824702" head="265.84" fix="2" route="18" stop="90000019" next="90000414" code="6" />
<bus time="250404173125" lat="64.12005145" lon="-21.8471476666667" head="103.51" fix="2" route="17" stop="90000137" next="90000138" code="6" />
<bus time="250404165308" lat="65.8655166666667" lon="-18.2618" head="353.17" fix="1" route="78" stop="65060001" next="65060002" code="6" />
<bus time="250404173121" lat="64.1394450333333" lon="-21.9203506666667" head="25.67" fix="2" route="18" stop="90000292" next="90000883" code="6" />
<bus time="250404173126" lat="64.1547932" lon="-21.7600603333333" head="238.53" fix="2" route="7" stop="90000443" next="90000471" code="6" />
<bus time="250404173125" lat="64.14815825" lon="-21.7722361666667" head="197.09" fix="2" route="6" stop="90000518" next="90000519" code="6" />
<bus time="250404173126" lat="64.1284474" lon="-21.8495935" head="177.18" fix="2" route="12" stop="90000193" next="90000138" code="3" />
<bus time="250404173122" lat="64.13941255" lon="-21.7880211666667" head="275.51" fix="2" route="31" stop="90000493" next="90000494" code="6" />
<bus time="250404173122" lat="64.1359792833333" lon="-21.9156473333333" head="294.96" fix="2" route="1" stop="90000483" next="90000844" code="6" />
<bus time="250404173123" lat="64.13641795" lon="-21.9209773333333" head="277.43" fix="2" route="6" stop="90000483" next="90000292" code="6" />
<bus time="250404172928" lat="64.14168365" lon="-21.9467421666667" head="138.56" fix="2" route="6" stop="90000882" next="90000881" code="4" />
<bus time="250404173122" lat="64.12752685" lon="-21.891848" head="122.92" fix="2" route="2" stop="90000287" next="90000083" code="6" />
<bus time="250404173122" lat="64.1466795333333" lon="-21.9431188333333" head="298.46" fix="2" route="2" stop="90000056" next="90000882" code="6" />
<bus time="250404173123" lat="64.1673058833333" lon="-21.6646831666667" head="270.18" fix="2" route="7" stop="16040666" next="16040667" code="2" />
<bus time="250404173122" lat="64.13887615" lon="-21.9398815" head="259.02" fix="2" route="1" stop="90000835" next="90000332" code="6" />
<bus time="250404173125" lat="64.1110464333333" lon="-21.9083368333333" head="298.09" fix="2" route="4" stop="10000974" next="10000814" code="6" />
<bus time="250404173125" lat="64.0436394166667" lon="-21.9568235" head="236.80" fix="2" route="1" stop="14001697" next="14001638" code="6" />
<bus time="250404173125" lat="64.1246622166667" lon="-21.8790335" head="27.20" fix="1" route="14" stop="90000435" next="90000557" code="6" />
<bus time="250404173125" lat="64.14881085" lon="-21.928036" head="42.20" fix="2" route="1" stop="90000875" next="90000713" code="2" />
<bus time="250404171145" lat="64.0535633333333" lon="-21.9703666666667" head="227.40" fix="2" route="1" stop="14001620" next="14001612" code="6" />
<bus time="250404173122" lat="64.1113690666667" lon="-21.9087998333333" head="195.33" fix="2" route="4" stop="10000972" next="10000859" code="6" />
<bus time="250404173102" lat="64.089085" lon="-21.9242" head="304.15" fix="2" route="24" stop="13001219" next="13001300" code="6" />
<bus time="250404173124" lat="64.07212785" lon="-21.9547468333333" head="207.47" fix="2" route="1" stop="14001527" next="14001528" code="6" />
<bus time="250404173121" lat="65.6641466666667" lon="-18.0831166666667" head="288.77" fix="2" route="A5" stop="60000066" next="60000067" code="6" />
<bus time="250404173123" lat="64.1049898333333" lon="-21.8169898333333" head="153.43" fix="2" route="4" stop="90000524" next="90000525" code="3" />
<bus time="250404173124" lat="64.1468625833333" lon="-21.8771445" head="258.60" fix="2" route="14" stop="90000250" next="90000251" code="6" />
<bus time="250404173122" lat="64.1106133333333" lon="-21.9064" head="287.50" fix="2" route="35" stop="10000893" next="10000973" code="6" />
<bus time="250404173126" lat="64.1346543666667" lon="-21.8846211666667" head="140.38" fix="2" route="11" stop="90000125" next="90000126" code="6" />
<bus time="250404173125" lat="64.1445915166667" lon="-21.9197896666667" head="113.82" fix="2" route="12" stop="90000823" next="90000878" code="3" />
<bus time="250404173126" lat="64.1482090166667" lon="-21.9269995" head="300.12" fix="2" route="17" stop="90000875" next="" code="6" />
<bus time="250404173124" lat="64.32045745" lon="-22.0703805" head="157.06" fix="2" route="57" stop="30001812" next="30001813" code="6" />
<bus time="250404173122" lat="64.1431467333333" lon="-21.9073433333333" head="186.09" fix="2" route="5" stop="90000212" next="90000030" code="2" />
<bus time="250404173126" lat="64.1530041333333" lon="-21.9522771666667" head="282.62" fix="2" route="14" stop="90000020" next="90000021" code="6" />
<bus time="250404173125" lat="64.1462831833333" lon="-21.9279825" head="295.05" fix="1" route="12" stop="90000821" next="90000054" code="6" />
<bus time="250404173126" lat="64.09914945" lon="-21.8266421666667" head="23.47" fix="1" route="3" stop="90000521" next="90000343" code="2" />
<bus time="250404173122" lat="64.1265291666667" lon="-21.8873721666667" head="21.37" fix="2" route="11" stop="90000084" next="90000288" code="6" />
<bus time="250404165758" lat="64.1008566666667" lon="-21.8769833333333" head="128.51" fix="2" route="2" stop="10000875" next="10000876" code="3" />
<bus time="250404173125" lat="64.1325751333333" lon="-21.7348178333333" head="277.50" fix="1" route="18" stop="90000650" next="90000651" code="6" />
<bus time="250404173121" lat="64.13633275" lon="-21.919194" head="280.97" fix="2" route="3" stop="90000483" next="90000844" code="6" />
<bus time="250404173122" lat="64.1061410666667" lon="-22.0097968333333" head="179.92" fix="2" route="23" stop="16031327" next="16031322" code="6" />
<bus time="250404173125" lat="64.1288846833333" lon="-21.9466731666667" head="298.30" fix="2" route="12" stop="90000201" next="90000329" code="6" />
<bus time="250404173125" lat="64.10657595" lon="-21.846503" head="65.90" fix="2" route="21" stop="10000875" next="90000862" code="6" />
<bus time="250404173124" lat="64.1097521666667" lon="-21.859693" head="93.37" fix="2" route="36" stop="10000936" next="10000853" code="6" />
<bus time="250404173121" lat="64.0994533333333" lon="-21.9137166666667" head="102.84" fix="1" route="2" stop="13001202" next="10000826" code="6" />
<bus time="250404173122" lat="64.1118433333333" lon="-21.90845" head="22.41" fix="2" route="28" stop="10000973" next="10000859" code="6" />
<bus time="250404173122" lat="64.1337367" lon="-21.9031295" head="112.84" fix="2" route="55" stop="90000460" next="90000015" code="6" />
<bus time="250404173124" lat="64.1457225833333" lon="-21.9009661666667" head="125.55" fix="2" route="4" stop="90000780" next="90000182" code="6" />
<bus time="250404162614" lat="64.089055" lon="-21.83675" head="77.84" fix="2" route="28" stop="10000911" next="10000920" code="6" />
<bus time="250404173125" lat="64.0340576" lon="-22.7009111666667" head="12.20" fix="2" route="89" stop="25030001" next="25030002" code="6" />
<bus time="250404173125" lat="64.0594270833333" lon="-21.9834775" head="110.44" fix="2" route="21" stop="14001686" next="14001680" code="6" />
<bus time="250404173125" lat="64.1563159" lon="-21.9410038333333" head="160.14" fix="2" route="3" stop="90000064" next="90000020" code="6" />
<bus time="250404173124" lat="63.9790455833333" lon="-22.3399883333333" head="60.36" fix="2" route="55" stop="25060005" next="14001500" code="6" />
<bus time="250404173124" lat="64.1411901333333" lon="-21.8983245" head="307.15" fix="1" route="15" stop="90000049" next="90000877" code="7" />
<bus time="250404170519" lat="63.99747" lon="-22.2642166666667" head="249.97" fix="2" route="55" stop="14001500" next="25060002" code="6" />
<bus time="250404173126" lat="64.1269932333333" lon="-21.9070373333333" head="111.93" fix="2" route="18" stop="90000302" next="90000132" code="6" />
<bus time="250404170535" lat="64.10523" lon="-21.8372666666667" head="314.18" fix="1" route="51" stop="90000752" next="90000864" code="6" />
<bus time="250404173125" lat="64.1391005166667" lon="-21.8933206666667" head="11.09" fix="2" route="4" stop="90000089" next="90000036" code="6" />
<bus time="250404173120" lat="64.1442069" lon="-21.9177526666667" head="293.27" fix="2" route="11" stop="90000879" next="90000052" code="6" />
<bus time="250404173122" lat="64.1142725666667" lon="-21.8431046666667" head="1.38" fix="1" route="57" stop="90000018" next="90000600" code="6" />
<bus time="250404173125" lat="64.1180281666667" lon="-21.7988321666667" head="32.50" fix="1" route="16" stop="90000733" next="90000734" code="6" />
<bus time="250404173044" lat="65.6836366666667" lon="-18.0895833333333" head="56.30" fix="2" route="A1" stop="60000069" next="60000070" code="6" />
<bus time="250404173122" lat="65.682895" lon="-18.0891" head="15.20" fix="1" route="A4" stop="60000001" next="60000069" code="6" />
<bus time="250404173123" lat="65.6940183333333" lon="-18.1430166666667" head="139.14" fix="2" route="A6" stop="60000089" next="60000087" code="6" />
<bus time="250404173126" lat="64.1084449166667" lon="-21.9059353333333" head="339.30" fix="2" route="1" stop="10000856" next="10000975" code="6" />
<bus time="250404171900" lat="64.169545" lon="-21.7065833333333" head="126.26" fix="2" route="15" stop="16040609" next="16040610" code="6" />
<bus time="250404173123" lat="64.0958158833333" lon="-21.8916038333333" head="120.53" fix="2" route="21" stop="10000904" next="13001587" code="6" />
<bus time="250404173124" lat="64.8229599166667" lon="-22.271646" head="156.23" fix="2" route="58" stop="37130001" next="36091900" code="6" />
<bus time="250404173124" lat="64.1382988833333" lon="-21.9328078333333" head="109.63" fix="2" route="3" stop="90000834" next="90000845" code="6" />
<bus time="250404173125" lat="64.1476218833333" lon="-21.9354563333333" head="40.49" fix="1" route="11" stop="90000001" next="90000002" code="6" />
<bus time="250404173125" lat="64.1376898333333" lon="-21.9224708333333" head="205.08" fix="2" route="6" stop="90000011" next="90000458" code="6" />
<bus time="250404173121" lat="64.1238308333333" lon="-21.8214563333333" head="88.51" fix="2" route="18" stop="90000018" next="90000757" code="6" />
<bus time="250404173124" lat="64.1297886166667" lon="-21.7279451666667" head="210.48" fix="2" route="18" stop="90000656" next="90000657" code="6" />
<bus time="250404173121" lat="64.08350305" lon="-21.8896483333333" head="71.61" fix="2" route="22" stop="13001593" next="13001594" code="6" />
<bus time="250404173122" lat="65.5536922833333" lon="-19.446134" head="127.11" fix="2" route="57" stop="52000002" next="52000001" code="6" />
<bus time="250404173124" lat="64.0679241166667" lon="-21.9579461666667" head="264.85" fix="2" route="1" stop="14001500" next="14001501" code="6" />
<bus time="250404173119" lat="64.3266590333333" lon="-22.063804" head="59.62" fix="2" route="57" stop="" next="35111819" code="6" />
<bus time="250404173125" lat="64.1324824333333" lon="-21.92968" head="303.01" fix="2" route="8" stop="90000009" next="90000835" code="6" />
<bus time="250404173119" lat="64.1238816666667" lon="-21.8218666666667" head="87.58" fix="2" route="6" stop="90000018" next="90000355" code="6" />
<bus time="250404173041" lat="64.15015365" lon="-21.7915601666667" head="294.30" fix="2" route="18" stop="90000366" next="90000500" code="4" />
<bus time="250404173122" lat="64.1363068" lon="-21.9553905" head="26.05" fix="2" route="15" stop="90000206" next="90000207" code="6" />
<bus time="250404173125" lat="64.0678643833333" lon="-21.9576755" head="339.89" fix="2" route="19" stop="14001500" next="14001668" code="6" />
<bus time="250404173125" lat="64.1346552166667" lon="-21.8131963333333" head="202.89" fix="2" route="6" stop="90000499" next="90000262" code="6" />
<bus time="250404172935" lat="64.1500942166667" lon="-21.7915855" head="284.23" fix="2" route="18" stop="90000366" next="90000500" code="4" />
<bus time="250404173125" lat="64.1576358666667" lon="-22.0014573333333" head="24.28" fix="2" route="11" stop="11000107" next="11000108" code="6" />
<bus time="250404173125" lat="64.0990020166667" lon="-21.9093921666667" head="282.74" fix="2" route="2" stop="10000825" next="13001204" code="6" />
<bus time="250404173125" lat="64.1096782166667" lon="-21.8427771666667" head="269.86" fix="2" route="4" stop="90000861" next="10000815" code="6" />
<bus time="250404173124" lat="64.1334177166667" lon="-21.8731026666667" head="240.19" fix="1" route="15" stop="90000034" next="90000224" code="6" />
<bus time="250404173126" lat="64.1096535" lon="-21.8421098333333" head="91.43" fix="2" route="3" stop="90000860" next="90000068" code="6" />
<bus time="250404173126" lat="63.9938918833333" lon="-22.5519003333333" head="332.60" fix="1" route="87" stop="20000007" next="25060007" code="6" />
<bus time="250404173125" lat="64.1280908166667" lon="-21.8710905" head="292.23" fix="1" route="17" stop="90000237" next="90000238" code="6" />
<bus time="250404173125" lat="64.1423782666667" lon="-21.9043861666667" head="112.25" fix="2" route="14" stop="90000030" next="90000031" code="6" />
<bus time="250404173125" lat="64.0568502" lon="-21.931215" head="227.54" fix="2" route="19" stop="14001674" next="14001676" code="6" />
<bus time="250404173126" lat="64.1206457" lon="-21.8086401666667" head="294.67" fix="2" route="5" stop="90000154" next="90000019" code="6" />
<bus time="250404173126" lat="64.1091271833333" lon="-21.7876066666667" head="192.87" fix="2" route="5" stop="90000405" next="90000406" code="6" />
<bus time="250404173118" lat="64.1274174166667" lon="-21.8129081666667" head="75.68" fix="1" route="24" stop="90000873" next="90000504" code="3" />
<bus time="250404173125" lat="64.1098960166667" lon="-21.8425828333333" head="291.42" fix="2" route="11" stop="90000863" next="90000076" code="6" />
<bus time="250404173123" lat="64.1255784166667" lon="-21.8240931666667" head="154.41" fix="1" route="24" stop="90000870" next="90000413" code="6" />
<bus time="250404173125" lat="64.1097027166667" lon="-21.843047" head="300.80" fix="2" route="3" stop="90000861" next="90000151" code="6" />
<bus time="250404173125" lat="63.9371281833333" lon="-21.0004486666667" head="4.62" fix="1" route="51" stop="82000006" next="82000011" code="6" />
<bus time="250404161631" lat="63.9436329166667" lon="-20.8501728333333" head="87.64" fix="1" route="73" stop="82000012" next="87200001" code="6" />
<bus time="250404173125" lat="64.1654420333333" lon="-21.6926705" head="322.86" fix="2" route="15" stop="16040622" next="16040619" code="6" />
<bus time="250404173125" lat="64.1379012166667" lon="-21.9091733333333" head="322.60" fix="2" route="13" stop="90000273" next="90000263" code="6" />
<bus time="250404173124" lat="64.1459599166667" lon="-21.9769116666667" head="295.15" fix="2" route="13" stop="90000276" next="11000100" code="6" />
<bus time="250404173125" lat="64.15987335" lon="-21.72628" head="324.08" fix="1" route="15" stop="16040604" next="16040606" code="6" />
<bus time="250404173126" lat="64.1236383" lon="-21.8944431666667" head="296.59" fix="2" route="13" stop="90000232" next="90000146" code="6" />
<bus time="250404173125" lat="64.14716055" lon="-21.9326418333333" head="294.68" fix="2" route="14" stop="90000054" next="90000833" code="6" />
<bus time="250404173126" lat="64.1281121" lon="-21.8939421666667" head="297.58" fix="1" route="2" stop="90000084" next="90000268" code="6" />
<bus time="250404173126" lat="64.1291685333333" lon="-21.9003653333333" head="180.24" fix="2" route="13" stop="90000286" next="90000287" code="6" />
<bus time="250404172955" lat="64.1482032" lon="-21.9268013333333" head="311.35" fix="1" route="16" stop="90000029" next="90000211" code="4" />
<bus time="250404173126" lat="64.1246567333333" lon="-21.823684" head="354.81" fix="2" route="12" stop="90000421" next="90000353" code="6" />
<bus time="250404173124" lat="64.0993635833333" lon="-21.9133351666667" head="117.99" fix="2" route="2" stop="13001202" next="10000826" code="6" />
<bus time="250404173123" lat="64.13880915" lon="-21.9402856666667" head="135.61" fix="2" route="2" stop="90000882" next="90000881" code="6" />
<bus time="250404173126" lat="64.13340595" lon="-21.9556235" head="121.27" fix="2" route="15" stop="90000257" next="90000204" code="6" />
<bus time="250404173125" lat="64.1456269833333" lon="-21.90673" head="247.42" fix="2" route="5" stop="90000877" next="90000252" code="6" />
</busstate>
