<busstate version="1.00" timestamp="2025-04-04 23:41:49">
<bus time="250404234144" lat="64.0894966" lon="-21.9323136666667" head="229.24" fix="1" route="1" stop="13001589" next="13001525" code="6" />
<bus time="250404234146" lat="64.1365476666667" lon="-21.8745951666667" head="323.22" fix="1" route="15" stop="90000046" next="90000047" code="6" />
<bus time="250404234148" lat="64.1401674166667" lon="-21.926519" head="56.60" fix="1" route="5" stop="90000829" next="90000830" code="2" />
<bus time="250404234147" lat="64.1116034166667" lon="-21.8870265" head="6.43" fix="1" route="4" stop="10000857" next="10000819" code="6" />
<bus time="250404234147" lat="64.1232400166667" lon="-21.8804228333333" head="197.98" fix="2" route="18" stop="90000423" next="90000080" code="6" />
<bus time="250404234143" lat="64.1483175833333" lon="-21.9273696666667" head="263.89" fix="1" route="1" stop="90000875" next="90000713" code="6" />
<bus time="250404234148" lat="64.1397973166667" lon="-21.8930753333333" head="7.31" fix="1" route="4" stop="90000089" next="90000036" code="6" />
<bus time="250404222656" lat="64.123645" lon="-21.8184166666667" head="267.22" fix="2" route="24" stop="90000260" next="90000261" code="6" />
<bus time="250404234146" lat="64.1498473333333" lon="-21.785501" head="105.63" fix="1" route="6" stop="90000367" next="90000633" code="6" />
<bus time="250404234144" lat="64.0533516666667" lon="-21.9710325" head="69.71" fix="1" route="1" stop="14001605" next="14001610" code="6" />
<bus time="250404234145" lat="64.1016446833333" lon="-21.8553836666667" head="62.33" fix="2" route="4" stop="90000432" next="90000433" code="6" />
<bus time="250404234146" lat="64.1476931166667" lon="-21.9823741666667" head="138.29" fix="1" route="11" stop="11000112" next="11000113" code="6" />
<bus time="250404234146" lat="64.1144846166667" lon="-21.8219946666667" head="23.40" fix="2" route="3" stop="90000453" next="90000073" code="6" />
<bus time="250404234053" lat="64.1098240833333" lon="-21.8427586666667" head="282.16" fix="2" route="11" stop="90000863" next="" code="4" />
<bus time="250404234148" lat="64.1448473" lon="-21.915104" head="193.50" fix="1" route="12" stop="90000876" next="90000052" code="6" />
<bus time="250404234017" lat="64.1234886833333" lon="-21.7881485" head="45.67" fix="2" route="3" stop="90000063" next="90000064" code="4" />
<bus time="250404234146" lat="64.0325222" lon="-22.0853526666667" head="66.03" fix="2" route="55" stop="25060005" next="14001500" code="6" />
<bus time="250404234147" lat="64.1322668" lon="-21.8937028333333" head="111.98" fix="1" route="3" stop="90000461" next="90000395" code="6" />
<bus time="250404234147" lat="64.1389828666667" lon="-21.939108" head="43.90" fix="2" route="6" stop="90000882" next="90000881" code="6" />
<bus time="250404234144" lat="64.3104231833333" lon="-21.9359816666667" head="274.94" fix="1" route="57" stop="90000705" next="30001822" code="6" />
<bus time="250404234148" lat="64.1361971166667" lon="-21.9323348333333" head="288.85" fix="1" route="1" stop="90000844" next="90000835" code="6" />
<bus time="250404234147" lat="64.1251831833333" lon="-21.7373228333333" head="128.98" fix="2" route="18" stop="90000269" next="90000551" code="6" />
<bus time="250404234146" lat="64.1342037333333" lon="-21.9047218333333" head="288.10" fix="2" route="6" stop="90000481" next="90000483" code="6" />
<bus time="250404234148" lat="64.14689535" lon="-21.931355" head="295.35" fix="2" route="11" stop="90000054" next="90000055" code="6" />
<bus time="250404234147" lat="64.0883813333333" lon="-21.8084708333333" head="36.59" fix="2" route="2" stop="10000824" next="10000945" code="6" />
<bus time="250404234147" lat="64.1012540833333" lon="-21.780843" head="129.23" fix="2" route="5" stop="90000129" next="90000397" code="6" />
<bus time="250404234145" lat="64.1075275666667" lon="-21.8525936666667" head="299.45" fix="1" route="24" stop="90000068" next="10000836" code="2" />
<bus time="250404234147" lat="63.9637931833333" lon="-21.1228271666667" head="143.32" fix="1" route="51" stop="87160002" next="82000004" code="6" />
<bus time="250404234147" lat="64.15019235" lon="-21.9431728333333" head="134.58" fix="2" route="13" stop="90000278" next="90000277" code="6" />
<bus time="250404234148" lat="64.1694807" lon="-21.714078" head="73.81" fix="1" route="15" stop="16040608" next="16040609" code="6" />
<bus time="250404234132" lat="64.1553044666667" lon="-21.8708063333333" head="134.07" fix="1" route="14" stop="90000022" next="90000001" code="4" />
<bus time="250404234147" lat="64.1387394166667" lon="-21.8505448333333" head="178.20" fix="1" route="12" stop="90000191" next="90000193" code="6" />
<bus time="250404234145" lat="64.1386861166667" lon="-21.8790053333333" head="134.80" fix="1" route="2" stop="90000032" next="90000033" code="3" />
<bus time="250404234148" lat="64.1403539333333" lon="-21.8885908333333" head="268.64" fix="2" route="5" stop="90000047" next="90000048" code="6" />
</busstate>
