<busstate version="1.00" timestamp="2025-04-04 23:09:16">
<bus time="250404230731" lat="64.1483097" lon="-21.9273016666667" head="258.38" fix="2" route="1" stop="90000875" next="90000713" code="4" />
<bus time="250404230912" lat="64.1505967666667" lon="-21.9861463333333" head="334.69" fix="1" route="13" stop="11000101" next="90000277" code="2" />
<bus time="250404230913" lat="64.1538541666667" lon="-21.6569898333333" head="351.09" fix="1" route="15" stop="16040617" next="16040621" code="6" />
<bus time="250404230914" lat="64.1306898666667" lon="-21.863523" head="311.41" fix="1" route="5" stop="90000039" next="90000041" code="6" />
<bus time="250404230915" lat="64.1472023166667" lon="-21.8957841666667" head="83.58" fix="2" route="14" stop="90000833" next="90000846" code="6" />
<bus time="250404230913" lat="64.14828185" lon="-21.9271481666667" head="264.79" fix="1" route="4" stop="90000875" next="90000776" code="6" />
<bus time="250404230914" lat="64.1510103666667" lon="-21.8827631666667" head="353.17" fix="1" route="12" stop="90000185" next="90000187" code="6" />
<bus time="250404230913" lat="64.1501763333333" lon="-21.791665" head="278.85" fix="1" route="18" stop="90000366" next="90000500" code="6" />
<bus time="250404230912" lat="64.1462600833333" lon="-21.8955358333333" head="272.99" fix="1" route="12" stop="90000164" next="90000165" code="6" />
<bus time="250404230914" lat="64.0932768" lon="-21.859994" head="131.16" fix="2" route="2" stop="10000964" next="10000966" code="6" />
<bus time="250404230912" lat="64.1295222333333" lon="-21.9000208333333" head="7.83" fix="1" route="1" stop="90000016" next="90000481" code="6" />
<bus time="250404230914" lat="64.0964749666667" lon="-21.8445391666667" head="63.84" fix="1" route="4" stop="90000428" next="90000429" code="6" />
<bus time="250404222656" lat="64.123645" lon="-21.8184166666667" head="267.22" fix="2" route="24" stop="90000260" next="90000261" code="6" />
<bus time="250404230910" lat="64.1398081833333" lon="-21.9425913333333" head="139.96" fix="1" route="6" stop="90000882" next="90000881" code="6" />
<bus time="250404230912" lat="64.0974676" lon="-21.920471" head="208.51" fix="2" route="1" stop="13001201" next="13001523" code="6" />
<bus time="250404230913" lat="64.1112851" lon="-21.8870968333333" head="7.10" fix="2" route="4" stop="10000857" next="10000819" code="6" />
<bus time="250404230914" lat="64.1474950333333" lon="-21.934869" head="106.76" fix="1" route="14" stop="90000001" next="90000002" code="6" />
<bus time="250404230908" lat="64.1089983333333" lon="-21.9088833333333" head="255.26" fix="2" route="35" stop="10000973" next="10000804" code="6" />
<bus time="250404230914" lat="64.1372802333333" lon="-21.8987276666667" head="291.24" fix="2" route="11" stop="90000090" next="90000091" code="6" />
<bus time="250404230910" lat="64.1016071833333" lon="-21.8994641666667" head="251.13" fix="1" route="2" stop="10000872" next="10000825" code="6" />
<bus time="250404230913" lat="64.1229405" lon="-21.8808333333333" head="96.99" fix="2" route="14" stop="90000133" next="90000435" code="6" />
<bus time="250404230914" lat="64.1356006166667" lon="-21.914455" head="108.96" fix="1" route="3" stop="90000458" next="90000460" code="6" />
<bus time="250404230914" lat="64.1411185666667" lon="-21.9555846666667" head="163.49" fix="1" route="11" stop="90000171" next="90000209" code="6" />
<bus time="250404230912" lat="64.10972675" lon="-21.8062121666667" head="300.88" fix="1" route="3" stop="90000449" next="90000450" code="6" />
<bus time="250404230913" lat="64.1251980666667" lon="-21.8237641666667" head="356.50" fix="1" route="12" stop="90000421" next="90000353" code="6" />
<bus time="250404230911" lat="64.1308548666667" lon="-21.8996333333333" head="12.37" fix="1" route="4" stop="90000016" next="90000461" code="6" />
<bus time="250404230756" lat="64.12348265" lon="-21.7881556666667" head="45.67" fix="2" route="3" stop="90000063" next="90000064" code="4" />
<bus time="250404230914" lat="63.9938471" lon="-22.551775" head="137.80" fix="2" route="55" stop="20000007" next="20000013" code="6" />
<bus time="250404230913" lat="64.1430173" lon="-21.9402418333333" head="68.59" fix="1" route="3" stop="90000003" next="90000004" code="6" />
<bus time="250404230911" lat="64.1296076666667" lon="-21.8752125" head="290.95" fix="2" route="6" stop="90000415" next="90000013" code="6" />
<bus time="250404230913" lat="64.1290257333333" lon="-21.8761251666667" head="195.63" fix="1" route="18" stop="90000414" next="90000422" code="6" />
<bus time="250404230911" lat="64.12459795" lon="-21.7876048333333" head="77.12" fix="1" route="57" stop="90000600" next="90000771" code="6" />
<bus time="250404230913" lat="64.0490083666667" lon="-21.9836545" head="313.61" fix="2" route="1" stop="14001661" next="14001615" code="6" />
<bus time="250404230813" lat="64.1480520333333" lon="-21.9266906666667" head="256.83" fix="1" route="18" stop="90000875" next="90000776" code="4" />
<bus time="250404230911" lat="64.14443265" lon="-21.7917848333333" head="47.70" fix="2" route="6" stop="90000531" next="90000532" code="6" />
<bus time="250404230914" lat="64.12719585" lon="-21.762951" head="86.51" fix="2" route="18" stop="90000290" next="90000264" code="6" />
<bus time="250404230807" lat="64.1098286166667" lon="-21.8425941666667" head="290.48" fix="2" route="11" stop="90000863" next="90000076" code="4" />
<bus time="250404230914" lat="64.14291025" lon="-21.9073933333333" head="182.29" fix="1" route="2" stop="90000212" next="90000030" code="6" />
<bus time="250404230913" lat="64.13754455" lon="-21.9323611666667" head="4.86" fix="1" route="5" stop="90000009" next="90000834" code="6" />
<bus time="250404230906" lat="64.0983728333333" lon="-21.9071178333333" head="6.35" fix="1" route="24" stop="13001223" next="13001207" code="6" />
<bus time="250404230602" lat="64.1346294833333" lon="-21.797594" head="112.76" fix="1" route="24" stop="90000358" next="90000359" code="3" />
<bus time="250404230910" lat="64.1009106833333" lon="-21.7621903333333" head="116.46" fix="1" route="51" stop="90000321" next="87160002" code="6" />
<bus time="250404230915" lat="64.1624068333333" lon="-21.7279685" head="26.04" fix="2" route="15" stop="16040604" next="16040606" code="6" />
<bus time="250404230913" lat="64.1236014333333" lon="-21.8944255" head="342.25" fix="1" route="13" stop="90000232" next="90000146" code="6" />
<bus time="250404230912" lat="64.1413436166667" lon="-21.9616663333333" head="185.62" fix="1" route="15" stop="90000172" next="90000173" code="6" />
<bus time="250404230908" lat="64.1552943833333" lon="-21.870788" head="134.07" fix="1" route="14" stop="90000022" next="90000001" code="4" />
<bus time="250404230914" lat="64.12623535" lon="-21.948753" head="11.95" fix="1" route="12" stop="90000200" next="90000201" code="6" />
<bus time="250404230912" lat="64.1445736333333" lon="-21.9152088333333" head="198.02" fix="1" route="2" stop="90000876" next="90000052" code="6" />
<bus time="250404230914" lat="64.1295314333333" lon="-21.8743976666667" head="290.28" fix="1" route="15" stop="90000415" next="90000239" code="6" />
<bus time="250404230914" lat="64.1091170833333" lon="-21.7876518333333" head="198.17" fix="1" route="5" stop="90000405" next="90000406" code="6" />
</busstate>
